nonebot_plugin_guess_disease/GuessDisease.py
nonebot_plugin_guess_disease/__init__.py
nonebot_plugin_guess_disease/config.py
nonebot_plugin_guess_disease/examples/diseases.json
nonebot_plugin_guess_disease-0.1.3.dist-info/WHEEL
nonebot_plugin_guess_disease-0.1.3.dist-info/METADATA
nonebot_plugin_guess_disease-0.1.3.dist-info/RECORD
