Metadata-Version: 2.3
Name: nonebot-plugin-guess-disease
Version: 0.1.3
Summary: 
Author: Xwei1645
Author-email: Xwei1645 <Xwei1645@gmail.com>
Requires-Dist: nonebot2>=2.4.2,<3.0.0
Requires-Dist: nonebot-adapter-onebot>=2.4.6,<3.0.0
Requires-Dist: nonebot-plugin-localstore>=0.7.4,<1.0.0
Requires-Dist: openai>=1.0.0
Requires-Dist: anyio>=4.8.0
Requires-Python: >=3.10, <3.13
Project-URL: Repository, https://github.com/Xwei1645/nonebot-plugin-guess-disease
